cherwellapi/__init__.py
cherwellapi/_version.py
cherwellapi/apiclient.py
cherwellapi/routers/__init__.py
cherwellapi/routers/relationships.py
cherwellapi/routers/search.py
cherwellapi/routers/translation.py
CherwellAPIClient-1.0.0.dist-info/LICENSE
CherwellAPIClient-1.0.0.dist-info/METADATA
CherwellAPIClient-1.0.0.dist-info/WHEEL
CherwellAPIClient-1.0.0.dist-info/top_level.txt
CherwellAPIClient-1.0.0.dist-info/RECORD
