Metadata-Version: 2.1
Name: CherwellAPIClient
Version: 1.0.0
Summary: Zenoss API client module
Author-email: Dan Smalley <cherwellapiclient@smalley.link>
Project-URL: Homepage, https://github.com/dan-smalley/CherwellAPIClient
Project-URL: Documentation, https://cherwellapiclient.readthedocs.io
Project-URL: Repository, https://github.com/dan-smalley/CherwellAPIClient.git
Keywords: zenoss,monitoring,api
Classifier: Intended Audience :: System Administrators
Classifier: License :: OSI Approved :: Apache Software License
Classifier: Natural Language :: English
Classifier: Programming Language :: Python :: 3
Classifier: Programming Language :: Python :: 3.12
Classifier: Topic :: Software Development :: Libraries :: Python Modules
Requires-Python: >=3.6
License-File: LICENSE
Requires-Dist: python-dateutil >=2.6.1
Requires-Dist: requests >=2.18.1
Provides-Extra: test
Requires-Dist: pytest >=3.2.3 ; extra == 'test'
Requires-Dist: pytest-responses >=0.4.0 ; extra == 'test'
Requires-Dist: versioneer ; extra == 'test'
